[ {
  "id" : -4845314532099889059,
  "title" : "Baltimore teen smacked by mom says he gets it",
  "description" : "Michael Singleton, 16, understands that his mother was trying to keep him out of trouble. FULL STORY",
  "source" : "CNN News",
  "date" : "2015-04-30T00:00:00.000Z"
}, {
  "id" : 3753275294638221896,
  "title" : "Protesting son: 'It was World War III' after mom saw me",
  "description" : "The Baltimore son who was slapped by his mother several times and pulled out of protests on live TV speaks to CNN's Anderson Cooper.",
  "source" : "CNN News",
  "date" : "2015-04-30T00:00:00.000Z"
}, {
  "id" : 6352332090196850781,
  "title" : "'Holding that line:' Portraits from Baltimore",
  "description" : "Photographer and Maryland Institute College of Art professor Nate Larson took portraits of police and protesters in Baltimore on April 28, a day after riots.",
  "source" : "CNN News",
  "date" : "2015-04-30T00:00:00.000Z"
}, {
  "id" : -212420911826772601,
  "title" : "Person close to officer offers information on Freddie Gray's arrest ",
  "description" : "Precious little is known about how exactly Freddie Gray died.",
  "source" : "CNN News",
  "date" : "2015-04-30T00:00:00.000Z"
}, {
  "id" : -6731596211524141322,
  "title" : "Baby pulled from quake rubble after 22 hours",
  "description" : "A photo of a baby boy being pulled from the rubble of the Nepal earthquake has become the defining image of a disaster that has devastated the country.",
  "source" : "CNN News",
  "date" : "2015-04-30T00:00:00.000Z"
}, {
  "id" : 34226701548965388,
  "title" : "FAA at first denied German pilot a medical certificate",
  "description" : "Years before Andreas Lubitz crashed a commercial airliner into the French Alps, the Federal Aviation Administration raised questions about his mental health, declining to give him a medical certificate.",
  "source" : "CNN News",
  "date" : "2015-04-30T00:00:00.000Z"
}, {
  "id" : 3768274008790151994,
  "title" : "Chilling photo: Tsarnaev's brother",
  "description" : "The defense is shifting the trial's focus to the power Tamerlan Tsarnaev held over Dzhokhar. FULL STORY",
  "source" : "CNN News",
  "date" : "2015-04-30T00:00:00.000Z"
}, {
  "id" : -4443163056432495672,
  "title" : "Man dies in oven, co-workers face charges",
  "description" : "Bumble Bee Foods and two employees face felony criminal charges in the 2012 death of Jose Melena, an employee who died in a pressure cooker. KCAL/KCBS reports.",
  "source" : "CNN News",
  "date" : "2015-04-30T00:00:00.000Z"
}, {
  "id" : 3760733311150294292,
  "title" : "Shark attack kills woman",
  "description" : "A woman died after a shark attack in Hawaii, prompting beach closures in nearby areas in Maui, authorities said.",
  "source" : "CNN News",
  "date" : "2015-04-30T00:00:00.000Z"
}, {
  "id" : 7701229868050991581,
  "title" : "Orioles have fun in 'fanless' game",
  "description" : "The smokey aroma of pulled pork from Boog Powell's BBQ stand wasn't wafting over the crowds Wednesday in downtown Baltimore's Eutaw Street.",
  "source" : "CNN News",
  "date" : "2015-04-30T00:00:00.000Z"
}, {
  "id" : 5153989057685023369,
  "title" : "Sanders will take on Clinton",
  "description" : "Bernie Sanders is in.",
  "source" : "CNN News",
  "date" : "2015-04-30T00:00:00.000Z"
}, {
  "id" : -7945948633149765753,
  "title" : "71 get life for torching church",
  "description" : "An Egyptian court has sentenced 71 people to life in prison for their role in the August 2013 burning of a Christian church in the Giza province village of Kafr Hakim, state news reports.",
  "source" : "CNN News",
  "date" : "2015-04-30T00:00:00.000Z"
}, {
  "id" : 5041080394578771265,
  "title" : "Russian spacecraft plunging to Earth",
  "description" : "The Russian cargo ship is carrying 3 tons of food, fuel, oxygen and spare parts, NASA says. FULL STORY",
  "source" : "CNN News",
  "date" : "2015-04-30T00:00:00.000Z"
}, {
  "id" : -3148201516010847431,
  "title" : "Report: Kim Jong Un had 15 officials executed",
  "description" : "North Korean leader Kim Jong Un is continuing to rule with an iron fist, having ordered the execution of about 15 senior officials so far this year, according to an assessment by South Korean intelligence agents, a lawmaker who attended a closed briefing said.",
  "source" : "CNN News",
  "date" : "2015-04-30T00:00:00.000Z"
}, {
  "id" : -7733681863891456954,
  "title" : "Police: TV star 'sexually abused' 22 students",
  "description" : "At least 22 pupils and a visitor at a former school for troubled girls in southeast England were sexually abused by the late British TV star Jimmy Savile in the 1970s, a report by Surrey police has concluded.",
  "source" : "CNN News",
  "date" : "2015-04-30T00:00:00.000Z"
}, {
  "id" : -1403161335689841658,
  "title" : "What happened to Bill Clinton's plane in Africa",
  "description" : "A plane carrying former President Bill Clinton stopped abruptly to have one of its engines fixed in Tanzania on Wednesday, multiple sources told CNN.",
  "source" : "CNN News",
  "date" : "2015-04-30T00:00:00.000Z"
}, {
  "id" : 6245884255118099978,
  "title" : "Weight Watchers founder Jean Nidetch dies at 91",
  "description" : "Combining healthy eating with moral support, Jean Nidetch became a heavyweight in the weight-loss industry. The founder of Weight Watchers died Wednesday at her home in Florida.",
  "source" : "CNN News",
  "date" : "2015-04-30T00:00:00.000Z"
}, {
  "id" : 7438927085594805570,
  "title" : "Homeless man gives church 18 cents, note",
  "description" : "A church in North Carolina received a touching note and offering from a homeless man. WBTV reports.",
  "source" : "CNN News",
  "date" : "2015-04-30T00:00:00.000Z"
}, {
  "id" : -2994856088364261714,
  "title" : "Joni Mitchell's friend files for conservatorship",
  "description" : "A longtime friend of Joni Mitchell has filed a legal petition seeking to be named the singer-songwriter's conservator.",
  "source" : "CNN News",
  "date" : "2015-04-30T00:00:00.000Z"
}, {
  "id" : 2094782425844756585,
  "title" : "Woman in Jaguar caught stealing packages",
  "description" : "A woman driving a Jaguar luxury car is caught on a homeowners security camera stealing a deliver off the front porch. KOMO's Lindsay Cohen reports.",
  "source" : "CNN News",
  "date" : "2015-04-30T00:00:00.000Z"
}, {
  "id" : 514367297759860353,
  "title" : "Look at me! 20 selfies of the week",
  "description" : "",
  "source" : "CNN News",
  "date" : "2015-04-30T00:00:00.000Z"
}, {
  "id" : 5164772147673043262,
  "title" : "Where in the world?",
  "description" : "Travel Photo of the Day",
  "source" : "CNN News",
  "date" : "2015-04-30T00:00:00.000Z"
}, {
  "id" : 7451843470021625030,
  "title" : "11 of the biggest upsets in boxing ",
  "description" : "Manny Pacquiao is a force to be reckoned with, but bookmakers still have him as a firm underdog in the lead up to Saturday's fight with Floyd Mayweather. We take you through the sport's biggest shocks and ask the question: can Manny rain on Floyd's parade?",
  "source" : "CNN News",
  "date" : "2015-04-30T00:00:00.000Z"
}, {
  "id" : 593697640990791735,
  "title" : "32 amazing sports photos",
  "description" : "",
  "source" : "CNN News",
  "date" : "2015-04-30T00:00:00.000Z"
}, {
  "id" : 3271223783621708473,
  "title" : "'Avengers:' From comics to screen",
  "description" : "Compare characters from the Marvel comics to the new \"Avengers: Age of Ultron\" movie.",
  "source" : "CNN News",
  "date" : "2015-04-30T00:00:00.000Z"
}, {
  "id" : -5344642960848863464,
  "title" : "'Revenge' is canceled -- what about your other TV faves?",
  "description" : "View this list of canceled TV shows to see which ones have gotten the ax.",
  "source" : "CNN News",
  "date" : "2015-04-30T00:00:00.000Z"
}, {
  "id" : -8513880865825582380,
  "title" : "Who's the world's sexiest woman?",
  "description" : "English actress Michelle Keegan has been named the sexiest woman in the world by British men's magazine FHM.",
  "source" : "CNN News",
  "date" : "2015-04-30T00:00:00.000Z"
}, {
  "id" : -8537317186084264995,
  "title" : "Singer injures vocal cords, cancels tour dates",
  "description" : "Sam Smith has been diagnosed with a hemorrhage to his vocal cords, and he's been ordered to stop performing until he's healthy.",
  "source" : "CNN News",
  "date" : "2015-04-30T00:00:00.000Z"
}, {
  "id" : 2819526631804682318,
  "title" : "From selfie stick to selfie arm?",
  "description" : "Selfie stick gets upgraded to selfie arm! CNN's Jeanne Moos reports it'll make selfies look less lonely.",
  "source" : "CNN News",
  "date" : "2015-04-30T00:00:00.000Z"
}, {
  "id" : -6406658938935251492,
  "title" : "SUV speeds through kids at bus stop",
  "description" : "A speeding car came within inches of hitting three children who were boarding a school bus in Graham, Washington. CNN affiliate KOMO reports.",
  "source" : "CNN News",
  "date" : "2015-04-30T00:00:00.000Z"
}, {
  "id" : 5625658868314510051,
  "title" : "World's fastest train takes you a mile in 10 seconds",
  "description" : "The Japanese Maglev train crushed its own world record by traveling at 374 miles per hour for nearly 11 seconds. Check out the train in action.",
  "source" : "CNN News",
  "date" : "2015-04-30T00:00:00.000Z"
}, {
  "id" : -997465757465108181,
  "title" : "Alligator trainer attacked during show ",
  "description" : "An alligator trainer was attacked while performing a show in Texas. CNN affiliate KTRK reports.",
  "source" : "CNN News",
  "date" : "2015-04-30T00:00:00.000Z"
}, {
  "id" : 6889949087074353882,
  "title" : "Surreal photos of classic fairy tales",
  "description" : "You don't have to be well-versed in Russian folklore to appreciate this dream-like take on classic stories.",
  "source" : "CNN News",
  "date" : "2015-04-30T00:00:00.000Z"
}, {
  "id" : 3216893777038591038,
  "title" : "Turning waves into mesmerizing mountains",
  "description" : "Australian coalminer-turned -photographer Ray Collins braves perilous conditions in storm-churned oceans to reveal a dreamlike world of frozen waves.",
  "source" : "CNN News",
  "date" : "2015-04-30T00:00:00.000Z"
}, {
  "id" : 8929085731062339908,
  "title" : "Look at trees in a different way ",
  "description" : "It all started by looking up.",
  "source" : "CNN News",
  "date" : "2015-04-30T00:00:00.000Z"
}, {
  "id" : 803899230659443669,
  "title" : "The week in 37 photos",
  "description" : "",
  "source" : "CNN News",
  "date" : "2015-04-30T00:00:00.000Z"
}, {
  "id" : 3982813884735457409,
  "title" : "100 choppers, 7,000 people, 24 hours",
  "description" : "",
  "source" : "CNN News",
  "date" : "2015-04-30T00:00:00.000Z"
}, {
  "id" : -430022272942440172,
  "title" : "A father goes 'badass' to save his family",
  "description" : "It happened 40 years ago, and it was a scene that could have been ripped from the script of \"Mission Impossible.\" This is the story of a Vietnam war hero you've never heard of.",
  "source" : "CNN News",
  "date" : "2015-04-30T00:00:00.000Z"
}, {
  "id" : 8104970883342764296,
  "title" : "Fall of Saigon memories remain fresh",
  "description" : "It's been 40 years since Communist forces took Saigon in the South and ended the Vietnam War. For those who lived through it, the memories remain fresh.",
  "source" : "CNN News",
  "date" : "2015-04-30T00:00:00.000Z"
}, {
  "id" : 7581577834594850291,
  "title" : "Scenes from the Vietnam War ",
  "description" : "",
  "source" : "CNN News",
  "date" : "2015-04-30T00:00:00.000Z"
}, {
  "id" : -7223209365092745626,
  "title" : "What you should know about the Vietnam War",
  "description" : "Here's some background information about the Vietnam War.",
  "source" : "CNN News",
  "date" : "2015-04-30T00:00:00.000Z"
}, {
  "id" : -9123883050224395304,
  "title" : "Believe your eyes: World photo awards",
  "description" : "",
  "source" : "CNN News",
  "date" : "2015-04-30T00:00:00.000Z"
}, {
  "id" : -2949811118652282746,
  "title" : "Singer of classic rock anthem dies",
  "description" : "When 19-year-old Jack Ely stepped into a Portland, Oregon, studio in 1963 to sing vocals on a low-budget cover of a little-known garage-rock song, he had no idea he was making music history.",
  "source" : "CNN News",
  "date" : "2015-04-30T00:00:00.000Z"
}, {
  "id" : -515600179241897855,
  "title" : "71 get life sentences for torching church",
  "description" : "An Egyptian court has sentenced 71 people to life in prison for their role in the August 2013 burning of a Christian church in the Giza province village of Kafr Hakim, state news reports.",
  "source" : "CNN News",
  "date" : "2015-04-30T00:00:00.000Z"
}, {
  "id" : -6263077740960651981,
  "title" : "Flatbread, fear on flight to Kathmandu",
  "description" : "",
  "source" : "CNN News",
  "date" : "2015-04-30T00:00:00.000Z"
}, {
  "id" : 7362621972367471911,
  "title" : "NASCAR pace car has surprise under the hood",
  "description" : "NASCAR's first-ever hydrogen fuel-cell pace car, the Toyota Mirai, burned zero fossil fuels and created zero air pollution at the 2015 Toyota Owners 400.",
  "source" : "CNN News",
  "date" : "2015-04-30T00:00:00.000Z"
}, {
  "id" : -9136251941688719909,
  "title" : "'Partridge Family' actress dies",
  "description" : "Suzanne Crough, the child actress who portrayed youngest daughter Tracy on the '70s musical sitcom \"The Partridge Family,\" has died. She was 52.",
  "source" : "CNN News",
  "date" : "2015-04-30T00:00:00.000Z"
}, {
  "id" : 7510184363276559328,
  "title" : "200 girls in terror camps saved",
  "description" : "Nigerian troops rescued 200 girls and 93 women Tuesday in the Sambisa Forest, the Nigerian Armed Forces announced on its official Twitter account.",
  "source" : "CNN News",
  "date" : "2015-04-30T00:00:00.000Z"
}, {
  "id" : -7114700408671240810,
  "title" : "Military develops self-steering bullet",
  "description" : "You know the phrase \"dodging a bullet\"? Forget about it. Probably not going to happen anymore.",
  "source" : "CNN News",
  "date" : "2015-04-30T00:00:00.000Z"
}, {
  "id" : 8847343882647164740,
  "title" : "100-million-year-old sea monster fossil found",
  "description" : "A farmer in Australia discovered a fossil belonging to a 100 million-year-old sea predator known as a \"Kronosaurus.\"",
  "source" : "CNN News",
  "date" : "2015-04-30T00:00:00.000Z"
} ]